Metadata-Version: 2.1
Name: kopl-engine-ubuntu
Version: 2022.4
Summary: Knowledge oriented Programing Language
Home-page: https://github.com/ShulinCao/KoPLEngine
Author: THU KEG
Author-email: 
License: UNKNOWN
Project-URL: Documents, https://kopl.xlore.cn/doc/
Platform: UNKNOWN
Classifier: Programming Language :: Python :: 3
Classifier: License :: OSI Approved :: MIT License
Classifier: Operating System :: POSIX :: Linux
Requires-Python: >=3.6
License-File: LICENSE
Requires-Dist: tqdm (>=4.62)
